graph_polisher/__init__.py
graph_polisher/cleaner.py
graph_polisher/configs.py
graph_polisher/tests/__init__.py
graph_polisher/tests/test_cleaner.py
graph_polisher-1.0.2.dist-info/LICENCE.txt
graph_polisher-1.0.2.dist-info/METADATA
graph_polisher-1.0.2.dist-info/WHEEL
graph_polisher-1.0.2.dist-info/top_level.txt
graph_polisher-1.0.2.dist-info/RECORD
