Metadata-Version: 2.1
Name: graph-polisher
Version: 1.0.2
Summary: graph-polisher is a library that helps you clean your plotly figures.. This library is inspired by the book Storytelling with Data by Cole Nussbaumer Knaflic (https://www.kobo.com/us/en/ebook/storytelling-with-data).
Home-page: https://gitlab.com/rigogsilva/graph-polisher
Author: Rodrigo da Silva
Author-email: dasil021@umn.edu
License: MIT
Platform: UNKNOWN
Classifier: Programming Language :: Python :: 3
Classifier: License :: OSI Approved :: MIT License
Classifier: Operating System :: OS Independent
Requires-Python: >=3.6
License-File: LICENCE.txt
